letloopit.py
letloop.py-0.1.6.dist-info/entry_points.txt
letloop.py-0.1.6.dist-info/WHEEL
letloop.py-0.1.6.dist-info/METADATA
letloop.py-0.1.6.dist-info/RECORD
